{
  "_note1": "KEEP THIS FILE! Check it into a version control system (VCS) like git.",
  "_note2": "ObjectBox manages crucial IDs for your object model. See docs for details.",
  "_note3": "If you have VCS merge conflicts, you must resolve them according to ObjectBox docs.",
  "entities": [
    {
      "id": "1:5431709523329762163",
      "lastPropertyId": "1:2674286678864797510",
      "name": "ContainerModel",
      "properties": [
        {
          "id": "1:2674286678864797510",
          "name": "_id"
        }
      ],
      "relations": [
        {
          "id": "1:3296401424871427172",
          "name": "elements"
        }
      ]
    },
    {
      "id": "2:3839830151068449270",
      "lastPropertyId": "2:3009567476473191354",
      "name": "ElementModel",
      "properties": [
        {
          "id": "1:5019099405291475077",
          "name": "_id"
        },
        {
          "id": "2:3009567476473191354",
          "name": "data"
        }
      ],
      "relations": []
    },
    {
      "id": "3:7459309208534282851",
      "lastPropertyId": "2:8245914255657310383",
      "name": "UnrelatedModel",
      "properties": [
        {
          "id": "1:3721835216981428962",
          "name": "_id"
        },
        {
          "id": "2:8245914255657310383",
          "name": "data"
        }
      ],
      "relations": []
    }
  ],
  "lastEntityId": "3:7459309208534282851",
  "lastIndexId": "0:0",
  "lastRelationId": "1:3296401424871427172",
  "lastSequenceId": "0:0",
  "modelVersion": 4,
  "modelVersionParserMinimum": 4,
  "retiredEntityUids": [],
  "retiredIndexUids": [],
  "retiredPropertyUids": [],
  "retiredRelationUids": [],
  "version": 1
}